functionlib/__init__.py
functionlib/functions.py
functionlib-0.1.0.dist-info/METADATA
functionlib-0.1.0.dist-info/WHEEL
functionlib-0.1.0.dist-info/top_level.txt
functionlib-0.1.0.dist-info/RECORD
