Metadata-Version: 2.1
Name: functionlib
Version: 0.1.0
Summary: FBI function library
Home-page: UNKNOWN
Author: Raymond
License: MIT
Platform: UNKNOWN
